{
  "version": "1.2.0",
  "title": "July 15, 2026 : Robot Policy Power Progress",
  "chapters": [
    {
      "startTime": 0,
      "title": "Introduction",
      "endTime": 19
    },
    {
      "startTime": 19,
      "title": "NVIDIA shares how to evaluate general-purpose robot policies for real-world deployment",
      "url": "https://www.therobotreport.com/nvidia-shares-how-evaluate-general-purpose-robot-policies-real-world-deployment/",
      "endTime": 69
    },
    {
      "startTime": 69,
      "title": "Key to Humanoid Progress: Managing the Power Behind the Robots",
      "url": "https://www.therobotreport.com/key-to-humanoid-progress-managing-the-power-behind-the-robots/",
      "endTime": 125
    },
    {
      "startTime": 125,
      "title": "ROS Discourse General: Ros2_info \u2014 a terminal workspace lens for ROS 2 (TUI + optional local AI)",
      "url": "https://discourse.openrobotics.org/t/ros2-info-a-terminal-workspace-lens-for-ros-2-tui-optional-local-ai/56590",
      "endTime": 191
    },
    {
      "startTime": 191,
      "title": "A flapping robot swims and flies like a diving bird",
      "url": "https://robohub.org/a-flapping-robot-swims-and-flies-like-a-diving-bird/",
      "endTime": 246
    },
    {
      "startTime": 246,
      "title": "ROS Discourse General: ROS2-DDSConfig-Optimizer Support CycloneDDS Now!",
      "url": "https://discourse.openrobotics.org/t/ros2-ddsconfig-optimizer-support-cyclonedds-now/56609",
      "endTime": 304
    },
    {
      "startTime": 304,
      "title": "Sign Off",
      "endTime": 318
    }
  ]
}